demos/sdk_output_skeleton_13_buildings/network.geojson
demos/sdk_output_skeleton_13_buildings/run/baseline_scenario/1/022_export_modelica_loads/building_loads.csv
demos/sdk_output_skeleton_13_buildings/run/baseline_scenario/10/022_export_modelica_loads/building_loads.csv
demos/sdk_output_skeleton_13_buildings/run/baseline_scenario/11/022_export_modelica_loads/building_loads.csv
demos/sdk_output_skeleton_13_buildings/run/baseline_scenario/12/022_export_modelica_loads/building_loads.csv
demos/sdk_output_skeleton_13_buildings/run/baseline_scenario/13/022_export_modelica_loads/building_loads.csv
demos/sdk_output_skeleton_13_buildings/run/baseline_scenario/2/022_export_modelica_loads/building_loads.csv
demos/sdk_output_skeleton_13_buildings/run/baseline_scenario/3/022_export_modelica_loads/building_loads.csv
demos/sdk_output_skeleton_13_buildings/run/baseline_scenario/4/022_export_modelica_loads/building_loads.csv
demos/sdk_output_skeleton_13_buildings/run/baseline_scenario/5/022_export_modelica_loads/building_loads.csv
demos/sdk_output_skeleton_13_buildings/run/baseline_scenario/6/022_export_modelica_loads/building_loads.csv
demos/sdk_output_skeleton_13_buildings/run/baseline_scenario/7/022_export_modelica_loads/building_loads.csv
demos/sdk_output_skeleton_13_buildings/run/baseline_scenario/8/022_export_modelica_loads/building_loads.csv
demos/sdk_output_skeleton_13_buildings/run/baseline_scenario/9/022_export_modelica_loads/building_loads.csv
demos/sdk_output_skeleton_13_buildings/run/baseline_scenario/ghe_dir/sys_params_proportional.json
demos/sdk_output_skeleton_13_buildings/run/baseline_scenario/ghe_dir/sys_params_upstream.json
demos/sdk_output_skeleton_1_ghe/network.geojson
demos/sdk_output_skeleton_1_ghe/run/baseline_scenario/8/022_export_modelica_loads/building_loads.csv
demos/sdk_output_skeleton_1_ghe/run/baseline_scenario/9/022_export_modelica_loads/building_loads.csv
thermalnetwork-0.4.1.dist-info/licenses/LICENSE
thermalnetwork-0.4.1.dist-info/METADATA
thermalnetwork-0.4.1.dist-info/WHEEL
thermalnetwork-0.4.1.dist-info/entry_points.txt
thermalnetwork-0.4.1.dist-info/top_level.txt
thermalnetwork-0.4.1.dist-info/RECORD
