Metadata-Version: 2.4
Name: ThermalNetwork
Version: 0.4.1
Summary: A thermal network solver for GHE sizing.
Author-email: Matt Mitchell <mitchute@gmail.com>, Nathan Moore <nathan.moore@nrel.gov>
Project-URL: Homepage, https://github.com/NREL/ThermalNetwork
Project-URL: Bug Tracker, https://github.com/NREL/ThermalNetwork/issues
Classifier: Development Status :: 4 - Beta
Classifier: Topic :: Scientific/Engineering
Classifier: Operating System :: OS Independent
Classifier: Programming Language :: Python :: 3.10
Classifier: Programming Language :: Python :: 3.11
Classifier: Programming Language :: Python :: 3.12
Classifier: Programming Language :: Python :: 3.13
Requires-Python: <3.14,>=3.10
License-File: LICENSE
Requires-Dist: click~=8.1
Requires-Dist: ghedesigner~=2.0
Requires-Dist: loguru~=0.7
Requires-Dist: pandas~=2.0
Requires-Dist: SecondaryCoolantProps~=1.3
Requires-Dist: scipy~=1.15
Provides-Extra: dev
Requires-Dist: pytest>=6.0; extra == "dev"
Requires-Dist: pytest-cov~=6.0; extra == "dev"
Requires-Dist: pytest-xdist~=3.6; extra == "dev"
Requires-Dist: pre-commit~=3.7; extra == "dev"
Requires-Dist: mkdocs-material~=9.5; extra == "dev"
Dynamic: license-file
